Workbook

Sheet Instructions
A1: Local Q&A evaluation scoresheet
A3: How to run
A4: 1. Open https://ng-04.github.io/news_sentiment/#local-qa and enter your Claude API key (model: claude-opus-5).
A5: 2. Use case A: add the folder data/A_Unstructured. Use case B: add data/B_Sales. For A7, add both folders together.
A6: 3. Before each question, set the Advanced settings shown in the 'Settings to use' column (re-index if chunk size changes).
A7: 4. Ask each question exactly as written, in a fresh chat (Clear chat) unless it is a follow-up.
A8: 5. Paste the answer into 'Actual answer', time it, and score it with the rubric. For chart questions, compare the proposal table with the reference before clicking Plot chart.
A10: Which cells to fill in
A11: Yellow cells in the 'Test cases' sheet: Actual answer, Score (0-2), Citations correct (Y/N), Made-up facts (Y/N), Seconds, Notes.
A12: Row 2 is a filled-in EXAMPLE showing the expected format; it is excluded from the Summary.
A14: Scoring rubric
A15: Score: 2 = correct and complete; 1 = partly correct, or honestly states a limitation; 0 = wrong, incomplete, or invents facts.
... A22: With small document sets, 'Answer from: Auto' sends Claude the complete documents, so 'list all' and 'table of every' questions (A1-A4) can be complete.

Sheet Summary
A1: Measure | B1: A: Unstructured | C1: B: Sales | D1: Cross-use-case | E1: All | F1: Target
A2: Questions in the test set | B2: =COUNTIF('Test cases'!$B$3:$B$21,"A: Unstructured") | C2: =COUNTIF('Test cases'!$B$3:$B$21,"B: Sales") | D2: =COUNTIF('Test cases'!$B$3:$B$21,"Cross-use-case") | E2: =COUNTA('Test cases'!$A$3:$A$21)
A3: Questions scored | B3: =COUNTIFS('Test cases'!$B$3:$B$21,"A: Unstructured",'Test cases'!$J$3:$J$21,"<>") | C3: =COUNTIFS('Test cases'!$B$3:$B$21,"B: Sales",'Test cases'!$J$3:$J$21,"<>") | D3: =COUNTIFS('Test cases'!$B$3:$B$21,"Cross-use-case",'Test cases'!$J$3:$J$21,"<>") | E3: =COUNT('Test cases'!$J$3:$J$21)
A4: Fully correct (score 2) | B4: =COUNTIFS('Test cases'!$B$3:$B$21,"A: Unstructured",'Test cases'!$J$3:$J$21,2) | C4: =COUNTIFS('Test cases'!$B$3:$B$21,"B: Sales",'Test cases'!$J$3:$J$21,2) | D4: =COUNTIFS('Test cases'!$B$3:$B$21,"Cross-use-case",'Test cases'!$J$3:$J$21,2) | E4: =COUNTIF('Test cases'!$J$3:$J$21,2)
A5: Accuracy (points / max) | B5: =IFERROR(SUMIFS('Test cases'!$J$3:$J$21,'Test cases'!$B$3:$B$21,"A: Unstructured")/(2*COUNTIFS('Test cases'!$B$3:$B$21,"A: Unstructured",'Test cases'!$J$3:$J$21,"<>")),"") | C5: =IFERROR(SUMIFS('Test cases'!$J$3:$J$21,'Test cases'!$B$3:$B$21,"B: Sales")/(2*COUNTIFS('Test cases'!$B$3:$B$21,"B: Sales",'Test cases'!$J$3:$J$21,"<>")),"") | D5: =IFERROR(SUMIFS('Test cases'!$J$3:$J$21,'Test cases'!$B$3:$B$21,"Cross-use-case")/(2*COUNTIFS('Test cases'!$B$3:$B$21,"Cross-use-case",'Test cases'!$J$3:$J$21,"<>")),"") | E5: =IFERROR(SUM('Test cases'!$J$3:$J$21)/(2*COUNT('Test cases'!$J$3:$J$21)),"") | F5: ≥ 85%
A6: Citations correct | B6: =IFERROR(COUNTIFS('Test cases'!$B$3:$B$21,"A: Unstructured",'Test cases'!$K$3:$K$21,"Y")/COUNTIFS('Test cases'!$B$3:$B$21,"A: Unstructured",'Test cases'!$K$3:$K$21,"?*"),"") | C6: =IFERROR(COUNTIFS('Test cases'!$B$3:$B$21,"B: Sales",'Test cases'!$K$3:$K$21,"Y")/COUNTIFS('Test cases'!$B$3:$B$21,"B: Sales",'Test cases'!$K$3:$K$21,"?*"),"") | D6: =IFERROR(COUNTIFS('Test cases'!$B$3:$B$21,"Cross-use-case",'Test cases'!$K$3:$K$21,"Y")/COUNTIFS('Test cases'!$B$3:$B$21,"Cross-use-case",'Test cases'!$K$3:$K$21,"?*"),"") | E6: =IFERROR(COUNTIF('Test cases'!$K$3:$K$21,"Y")/COUNTIF('Test cases'!$K$3:$K$21,"?*"),"") | F6: ≥ 95%
A7: Answers with made-up facts | B7: =COUNTIFS('Test cases'!$B$3:$B$21,"A: Unstructured",'Test cases'!$L$3:$L$21,"Y") | C7: =COUNTIFS('Test cases'!$B$3:$B$21,"B: Sales",'Test cases'!$L$3:$L$21,"Y") | D7: =COUNTIFS('Test cases'!$B$3:$B$21,"Cross-use-case",'Test cases'!$L$3:$L$21,"Y") | E7: =COUNTIF('Test cases'!$L$3:$L$21,"Y") | F7: 0
A8: Average seconds per answer | B8: =IFERROR(AVERAGEIFS('Test cases'!$M$3:$M$21,'Test cases'!$B$3:$B$21,"A: Unstructured"),"") | C8: =IFERROR(AVERAGEIFS('Test cases'!$M$3:$M$21,'Test cases'!$B$3:$B$21,"B: Sales"),"") | D8: =IFERROR(AVERAGEIFS('Test cases'!$M$3:$M$21,'Test cases'!$B$3:$B$21,"Cross-use-case"),"") | E8: =IFERROR(AVERAGE('Test cases'!$M$3:$M$21),"") | F8: < 20
A10: All values are formulas over the 'Test cases' sheet (the EXAMPLE row is outside the counted range).

Sheet Test cases
A1: ID | B1: Use case | C1: Question type | D1: Question | E1: Reference answer | F1: Key facts to check | G1: Pass criteria | H1: Settings to use | I1: Actual answer | J1: Score (0-2) | K1: Citations correct (Y/N) | L1: Made-up facts (Y/N) | M1: Seconds | N1: Notes
A2: EX | B2: Example | C2: Lookup | D2: What discount did Ember get in April? | E2: 25% clearance | F2: 25% | G2: 2 = number + reason | H2: Default | I2: Ember Room Heater had a 25% clearance discount in April [1]. | J2: 2 | K2: Y | L2: N | M2: 6 | N2: EXAMPLE row: excluded from the Summary
A3: A1 | B3: A: Unstructured | C3: Extraction to table | D3: Create a table of all customer calls with customer, city, date, product, main issue, sentiment, follow-up owner and due date. | E3: A 12-row table: Customer | City | Date | Product | Main issue | Sentiment | Owner | Due Meridian Foods | Pune | 2 Sep 2026 | Cascade Water Purifier | Filter cartridge availability | Negative | Ravi Menon | 10 Sep 2026 Sunrise Retail | Mumbai | 3 Sep 2026 | Halo Smart Bulb | App pairing problems | Neutral | Priya Shah | 15 Sep 2026 GreenLeaf Hotels | Bengaluru | 4 Sep 2026 | Drift Air Cooler | Delivery delays | Negative | Arjun Rao | 8 Sep 2026 Kaveri Distributors | Chennai | 5 Sep 2026 | Cascade Water Purifier | Filter cartridge availability | Negative | Ravi Menon | 12 Sep 2026 Urban Nest Interiors | Delhi | 8 Sep 2026 | Glow LED Lamp | None (positive feedback) | Positive | Neha Gupta | 30 Sep 2026 Coastal Mart | Kochi | 9 Sep 2026 | Breeze Fan | Price higher than competitor | Neutral | Arjun Rao | 20 Sep 2026 Sapphire Electronics | Hyderabad | 11 Sep 2026 | Flux Mixer Grinder | Delivery delays | Negative | Priya Shah | 18 Sep 2026 Himalaya Stores | Dehradun | 12 Sep 2026 | Ember Room Heater | None (pre-season order) | Positive | Neha Gupta | 25 Sep 2026 TechHome Solutions | Bengaluru | 15 Sep 2026 | Halo Smart Bulb | App pairing problems | Negative | Priya Shah | 22 Sep 2026 Annapurna Caterers | Pune | 16 Sep 2026 | Aurora Kettle | Delivery delays | Neutral | Arjun Rao | 19 Sep 2026 BrightPath Schools | Lucknow | 18 Sep 2026 | Halo Smart Bulb | App pairing problems | Neutral | Priya Shah | 29 Sep 2026 Delta Supermarkets | Ahmedabad | 22 Sep 2026 | Cascade Water Purifier | Filter cartridge availability; Price higher than competitor | Neutral | Ravi Menon | 1 Oct 2026 | F3: All 12 customers present; owners and due dates match; sentiment reasonable (Negative for Meridian, GreenLeaf, Kaveri, Sapphire, TechHome). | G3: 2 = all 12 rows correct; 1 = 9-11 rows or minor field errors; 0 = <9 rows or invented rows. | H3: Default settings (Answer from: Auto reads all documents); Max answer length 1500+
A4: A2 | B4: A: Unstructured | C4: Insight | D4: What are the most common complaints across the customer calls? Count how many calls mention each. | E4: Halo app pairing problems: 3 calls (Sunrise, TechHome, BrightPath). Cascade filter cartridge availability: 3 (Meridian, Kaveri, Delta). Delivery delays: 3 (GreenLeaf, Sapphire, Annapurna). Price higher than competitor: 2 (Coastal Mart vs CoolWind, Delta vs AquaPure). | F4: Three themes tied at 3 calls each; price as a 4th theme with 2. | G4: 2 = all themes with right counts; 1 = right themes, wrong counts; 0 = wrong themes. | H4: Default settings (Answer from: Auto)
A5: A3 | B5: A: Unstructured | C5: Insight | D5: Which customers are at risk of moving to a competitor, and why? | E5: Meridian Foods (Pune): no filter cartridges, evaluating AquaPure, 40-unit order on hold. Kaveri Distributors (Chennai): stock and cartridge shortage, AquaPure offering better margins. TechHome Solutions (Bengaluru): Halo pairing failures, trialling LumaSmart, orders paused. | F5: Exactly these 3; competitor names AquaPure, AquaPure, LumaSmart. | G5: 2 = all 3 with reasons; 1 = 2 of 3; 0 = fewer or invented. | H5: Default settings (Answer from: Auto)
A6: A4 | B6: A: Unstructured | C6: Extraction to table | D6: List the follow-up actions due on or before 15 September 2026, with owner and due date, as a table. | E6: GreenLeaf Hotels: apology + credit note, Arjun Rao, 8 Sep. Meridian Foods: cartridge delivery date, Ravi Menon, 10 Sep. Kaveri Distributors: stock plan, Ravi Menon, 12 Sep. Sunrise Retail: app update timeline, Priya Shah, 15 Sep. | F6: Exactly 4 actions. | G6: 2 = exactly these 4; 1 = 3 correct or 1 extra; 0 otherwise. | H6: Default settings (Answer from: Auto)
A7: A5 | B7: A: Unstructured | C7: Extraction to table | D7: From the store visit reports, make a table of stock-outs: store, region, product, how many days, visit date. | E7: Store | Region | Product | Days | Visit date Chennai, Anna Nagar | South | Cascade Water Purifier | 9 days | 12 Aug 2026 Bengaluru, Indiranagar | South | Cascade Water Purifier | 6 days | 14 Aug 2026 Mumbai, Andheri | West | Glow LED Lamp | 4 days | 20 Aug 2026 Hyderabad, Banjara Hills | South | Cascade Water Purifier | 11 days | 25 Aug 2026 | F7: 4 rows: 3 Cascade Water Purifier stock-outs in South stores + Glow LED Lamp in Mumbai. | G7: 2 = all 4 correct; 1 = 3 correct; 0 otherwise. | H7: Default settings
A8: A6 | B8: A: Unstructured | C8: Summary | D8: Summarise what competitors are doing according to the store visits and customer calls. | E8: AquaPure: purifier at ₹11,499 (about ₹1,500 below Cascade) in Chennai, festive promotion in Hyderabad, better margins offered to Kaveri, mentioned by Meridian and Delta. CoolWind: fans about 10% cheaper (Delhi store, Coastal Mart). LumaSmart: smart bulb trial at TechHome. | F8: AquaPure, CoolWind, LumaSmart with the right products. | G8: 2 = all three; 1 = two; 0 = one or invented competitors. | H8: Default settings (Answer from: Auto)
A9: A7 | B9: Cross-use-case | C9: Cross-document insight | D9: Do the store visit reports or customer calls explain any dip in the sales data? | E9: Yes: Cascade Water Purifier sales in the South fell in August (136 units in July to 35 in August) because South stores (Chennai, Bengaluru, Hyderabad) were out of stock; the commentary blames missed supplier shipments. Sales recovered in September (150). Customers Kaveri and Meridian also cite cartridge/stock shortages. | F9: Links the South August purifier dip to the stock-outs, cites both sales data and visit reports. | G9: 2 = link made with evidence from both sources; 1 = link made, one source; 0 = no link or wrong cause. | H9: Load A and B folders together; default settings
A10: A8 | B10: A: Unstructured | C10: Negative (not in documents) | D10: What did customers say about the warranty extension programme? | E10: Not in the documents. The tool should say it couldn't find this, with a 'How I checked' table giving each of the documents and why it can't answer. | F10: Must not invent anything; every document checked. | G10: 2 = not found with a check per document; 1 = not found without the checks; 0 = any invented content. | H10: Default settings
A11: A9 | B11: A: Unstructured | C11: Derived count | D11: How many store visits were there per month? | E11: 6 store visits, all in August 2026 (12, 14, 18, 20, 22 and 25 August); none in any other month. | F11: 6 visits, all August. | G11: 2 = 6 in August and none elsewhere; 1 = August only or wrong count; 0 = 'not found' or invented months. | H11: Default settings (found in real testing: an over-strict prompt made the tool answer 'not found')
A12: B1 | B12: B: Sales | C12: Lookup | D12: What discount was given on the Ember Room Heater in April 2026, and why? | E12: 25% clearance discount (April and May) to reduce winter stock; standard home comfort discount is 8%. | F12: 25%, clearance reason. | G12: 2 = both; 1 = number only; 0 = wrong. | H12: Default settings
A13: B2 | B13: B: Sales | C13: Narrative | D13: Why did Drift Air Cooler sales peak in May? | E13: A heatwave across North and West India in May (commentary); sales eased from July with the monsoon. | F13: Heatwave, May. | G13: 2 = cause + timing; 1 = cause only; 0 = wrong. | H13: Default settings
A14: B3 | B14: B: Sales | C14: Chart (exact numbers) | D14: Plot monthly units sold of Drift Air Cooler as a line chart. | E14: Proposal table, then line chart with all regions summed: April 1,095; May 1,469; June 1,150; July 598; August 398; September 323. | F14: Values match exactly; source shows Sales_FY27_H1.xlsx sheet Transactions. | G14: 2 = exact values and plotted after confirm; 1 = right shape, wrong grouping; 0 = wrong numbers. | H14: Default settings
... A21: B10 | B21: B: Sales | C21: Negative (not in documents) | D21: What were sales in October 2026? | E21: Not in the data (the data covers April to September 2026). Should say it couldn't find this. | F21: Must not invent October figures. | G21: 2 = says not found / data ends September; 0 = any invented figure. | H21: Default settings
